cheetah_lint/__init__.py
cheetah_lint/directives.py
cheetah_lint/flake.py
cheetah_lint/imports.py
cheetah_lint/reorder_imports.py
cheetah_lint/util.py
cheetah_lint-1.4.0.dist-info/LICENSE
cheetah_lint-1.4.0.dist-info/METADATA
cheetah_lint-1.4.0.dist-info/WHEEL
cheetah_lint-1.4.0.dist-info/entry_points.txt
cheetah_lint-1.4.0.dist-info/top_level.txt
cheetah_lint-1.4.0.dist-info/RECORD
