Metadata-Version: 2.1
Name: cheetah-lint
Version: 1.4.0
Summary: Linting tools for the Cheetah templating language.
Home-page: https://github.com/asottile/cheetah_lint
Author: Anthony Sottile
Author-email: asottile@umich.edu
License: MIT
Classifier: License :: OSI Approved :: MIT License
Classifier: Programming Language :: Python :: 3
Classifier: Programming Language :: Python :: 3 :: Only
Classifier: Programming Language :: Python :: Implementation :: CPython
Requires-Python: >=3.8
License-File: LICENSE
Requires-Dist: classify-imports
Requires-Dist: flake8 (>=6)
Requires-Dist: refactorlib[cheetah] (<=0.15.999,>=0.15.0)
Requires-Dist: yelp-cheetah (<=0.19.999,>=0.19.0)
